README.md
pyproject.toml
setup.cfg
setup.py
mmp_theme/__init__.py
mmp_theme/mmp_plot.py
mmp_theme/mmp_theme.py
mmp_theme.egg-info/PKG-INFO
mmp_theme.egg-info/SOURCES.txt
mmp_theme.egg-info/dependency_links.txt
mmp_theme.egg-info/requires.txt
mmp_theme.egg-info/top_level.txt