Metadata-Version: 2.1
Name: mmp-theme
Version: 1.2.1
Summary: Custom theme and functions for MMP plots
Home-page: https://source.cloud.google.com/mmp-vm/utility_repo/+/master:mmp_theme/
Author: Giulia Bortolato
Author-email: giulia.bortolato@milanomultiphysics.com
License: MIT
Download-URL: https://github.com/giulia-mmp/mmp_theme/archive/refs/tags/v1.2.1.tar.gz
Platform: UNKNOWN
